{
    "290806183969816586": {
        "username": "sankyaku#0001",
        "avatar_url": "https://cdn.discordapp.com/avatars/290806183969816586/a_920996ccba11f7a3fe530ddcff3e822d.png",
        "avatar_id": "a_920996ccba11f7a3fe530ddcff3e822d",
        "phone_number": "+6281255333053",
        "email": "a.prewandha@gmail.com",
        "mfa_enabled": true,
        "flags": 288,
        "locale": "en-US",
        "verified": true,
        "has_nitro": true,
        "payment_methods": 0,
        "token": "MjkwODA2MTgzOTY5ODE2NTg2.G508e8.HD-Xtpw3CQPh8-xkZKiRb36uOJUEqwbaN8nHx0"
    },
    "932833117725687808": {
        "username": "Shre_15#3766",
        "avatar_url": "https://cdn.discordapp.com/avatars/932833117725687808/6c77212d2fb712ba17ee0328af2cc703.png",
        "avatar_id": "6c77212d2fb712ba17ee0328af2cc703",
        "phone_number": "+918168810288",
        "email": "ninychoudhary77@gmail.com",
        "mfa_enabled": false,
        "flags": 128,
        "locale": "en-US",
        "verified": true,
        "has_nitro": false,
        "payment_methods": 0,
        "token": "OTMyODMzMTE3NzI1Njg3ODA4.GsJabK.-j9jcvqNtHj0Ucs5fl49slaUAQw_4AhCulE0B0"
    },
    "770325753245990942": {
        "username": "NiX#8920",
        "avatar_url": "https://cdn.discordapp.com/avatars/770325753245990942/6c4adb19bff23756db9fce3ceb62a3df.png",
        "avatar_id": "6c4adb19bff23756db9fce3ceb62a3df",
        "phone_number": null,
        "email": "ahmed.2060620@gmail.com",
        "mfa_enabled": false,
        "flags": 64,
        "locale": "en-US",
        "verified": true,
        "has_nitro": false,
        "payment_methods": 0,
        "token": "NzcwMzI1NzUzMjQ1OTkwOTQy.Gl_z6R.zbP-QyRzW1Vxr2wtKK-TI6Jnviw39W8UhINlFg"
    },
    "760140916857110601": {
        "username": "Mitsuki.#0210",
        "avatar_url": "https://cdn.discordapp.com/avatars/760140916857110601/874fcfa61faf0f7d5e63df5549d228ec.png"
    },
    "567738645637758977": {
        "username": "defurl#1874",
        "avatar_url": "https://cdn.discordapp.com/avatars/567738645637758977/2ee91cf008690421a8ef201f7d11a657.png",
        "avatar_id": "2ee91cf008690421a8ef201f7d11a657",
        "phone_number": "+84347385690",
        "email": "tiktokdefurl@gmail.com",
        "mfa_enabled": true,
        "flags": 16,
        "locale": "en-US",
        "verified": true,
        "has_nitro": false,
        "payment_methods": 0,
        "token": "NTY3NzM4NjQ1NjM3NzU4OTc3.Gnbq5D.ZPSHLq3FryugDP6PCDknp8qeePtXjELlRLJYMY"
    },
    "570522767259205634": {
        "username": "Breakers Live#9916",
        "avatar_url": "https://cdn.discordapp.com/avatars/570522767259205634/9eb005c9ca3891c33e6c587c6751c937.png"
    },
    "658782275764486226": {
        "username": "zenkento#3488",
        "avatar_url": "https://cdn.discordapp.com/avatars/658782275764486226/3b041d5543e3460824103d8aa3557c6b.png"
    },
    "876206088645652500": {
        "username": "Victor\u5200#5302",
        "avatar_url": "https://cdn.discordapp.com/avatars/876206088645652500/aff828766d913a46583f46cde225c2b7.png",
        "avatar_id": "aff828766d913a46583f46cde225c2b7",
        "phone_number": null,
        "email": "uzumakidatebaioyoutobe@gmail.com",
        "mfa_enabled": false,
        "flags": 128,
        "locale": "en-GB",
        "verified": true,
        "has_nitro": false,
        "payment_methods": 0,
        "token": "ODc2MjA2MDg4NjQ1NjUyNTAw.GQGcSo.e-1OyQzUMsmTFnBU5VV3M1IVy-uu-0IQePBbWU"
    },
    "505288627551469568": {
        "username": "agntpanda.ttv#0422",
        "avatar_url": "https://cdn.discordapp.com/avatars/505288627551469568/da573467ef972d8a043fdbc7baa515e1.png",
        "avatar_id": "da573467ef972d8a043fdbc7baa515e1",
        "phone_number": "+9779815201000",
        "email": "agntpanda@gmail.com",
        "mfa_enabled": false,
        "flags": 32,
        "locale": "en-US",
        "verified": true,
        "has_nitro": false,
        "payment_methods": 0,
        "token": "NTA1Mjg4NjI3NTUxNDY5NTY4.GQM3_J.MbEbm99P-KZxtu1TwXvUdgDYJe70O72Ow7KGS4"
    },
    "430916606865047553": {
        "username": "ryce#2441",
        "avatar_url": "https://cdn.discordapp.com/avatars/430916606865047553/a05bf2c1499b4025d18867d71c33afa9.png"
    },
    "639089808144072745": {
        "username": "\uff24\uff41\uff52\uff4b_S o l d i e r \u706b\u30f2\u5fdc (no mic)#3915",
        "avatar_url": "https://cdn.discordapp.com/avatars/639089808144072745/0272cce7d87430d39fa1e30a4ee10461.png",
        "avatar_id": "0272cce7d87430d39fa1e30a4ee10461",
        "phone_number": null,
        "email": "azevyinsta@gmail.com",
        "mfa_enabled": false,
        "flags": 0,
        "locale": "fr",
        "verified": true,
        "has_nitro": false,
        "payment_methods": 0,
        "token": "NjM5MDg5ODA4MTQ0MDcyNzQ1.GozcRY.VzR3a2d_WS5MtpXEBH777GIjD_RnnZ7nLZZ7TE"
    },
    "543346694482296832": {
        "username": "wuddz#9554",
        "avatar_url": "https://cdn.discordapp.com/avatars/543346694482296832/e7c51f366f63fc047340cb4f272d84e1.png"
    },
    "333342615514775554": {
        "username": ".Ground61#6161",
        "avatar_url": "https://cdn.discordapp.com/avatars/333342615514775554/a_9430e2ffcea0ac5d14c8effe59929518.png",
        "avatar_id": "a_9430e2ffcea0ac5d14c8effe59929518",
        "phone_number": null,
        "email": "berkay61bb@gmail.com",
        "mfa_enabled": false,
        "flags": 32,
        "locale": "de",
        "verified": true,
        "has_nitro": true,
        "payment_methods": 0,
        "token": "MzMzMzQyNjE1NTE0Nzc1NTU0.GqxpwI.Ceiy9nKcuaBfEiB44oSoBeLBeqbqOdhk9D4MY4"
    },
    "909072769965240320": {
        "username": "sewey#9063",
        "avatar_url": "https://cdn.discordapp.com/avatars/909072769965240320/0.png"
    },
    "502178897027268619": {
        "username": "Kaito#2776",
        "avatar_url": "https://cdn.discordapp.com/avatars/502178897027268619/970efeb66bf020c54c8e1718ac391e96.png",
        "avatar_id": "970efeb66bf020c54c8e1718ac391e96",
        "phone_number": "+33601939063",
        "email": "legrand.mael45@gmail.com",
        "mfa_enabled": false,
        "flags": 160,
        "locale": "fr",
        "verified": true,
        "has_nitro": false,
        "payment_methods": 0,
        "token": "NTAyMTc4ODk3MDI3MjY4NjE5.GxfyhF.b_zzyqgJVLNIOumPnOeYohXGi-58bY3VpPm4nQ"
    },
    "849559967106072576": {
        "username": "Damon#2377",
        "avatar_url": "https://cdn.discordapp.com/avatars/849559967106072576/641ea524f5de8dcf2fc726fa3ef176b9.png",
        "avatar_id": "641ea524f5de8dcf2fc726fa3ef176b9",
        "phone_number": null,
        "email": "kimaconnie89@gmail.com",
        "mfa_enabled": false,
        "flags": 0,
        "locale": "en-US",
        "verified": true,
        "has_nitro": false,
        "payment_methods": 0,
        "token": "ODQ5NTU5OTY3MTA2MDcyNTc2.Gctujn.ye01IIv3EcM6vVk1wr09g_E6bFJuLAVGJivHuI"
    },
    "827161421510869002": {
        "username": "cherlyn#3924",
        "avatar_url": "https://cdn.discordapp.com/avatars/827161421510869002/0.png",
        "avatar_id": null,
        "phone_number": null,
        "email": "losty6844@hotmail.com",
        "mfa_enabled": false,
        "flags": 0,
        "locale": "en-GB",
        "verified": true,
        "has_nitro": false,
        "payment_methods": 0,
        "token": "ODI3MTYxNDIxNTEwODY5MDAy.GdP22p.ay9wTAWwE18lr_06voZdWOkvrK03UWijuV6VHk"
    },
    "978530867423096862": {
        "username": "Arish#1602",
        "avatar_url": "https://cdn.discordapp.com/avatars/978530867423096862/cf728242e141cd497db35b3193b20c38.png",
        "avatar_id": "cf728242e141cd497db35b3193b20c38",
        "phone_number": null,
        "email": "arishamv90@gmail.com",
        "mfa_enabled": false,
        "flags": 0,
        "locale": "en-GB",
        "verified": true,
        "has_nitro": false,
        "payment_methods": 0,
        "token": "OTc4NTMwODY3NDIzMDk2ODYy.GcygRf.KIShfm_WJtV5bDnWOdFV17IT_YoI9PR-D01LTU"
    },
    "935106803405037588": {
        "username": "MiyaMuriM#3561",
        "avatar_url": "https://cdn.discordapp.com/avatars/935106803405037588/ca3c86c320b06ccb2218f9749e892354.png",
        "avatar_id": "ca3c86c320b06ccb2218f9749e892354",
        "phone_number": "+48510764582",
        "email": "panryz@onet.pl",
        "mfa_enabled": false,
        "flags": 64,
        "locale": "pl",
        "verified": true,
        "has_nitro": true,
        "payment_methods": 1,
        "token": "OTM1MTA2ODAzNDA1MDM3NTg4.GU40Ko.v4f4gFLL8LdPS136qMHQ7spOJuAfAksY-dY-P0"
    },
    "718895702914367600": {
        "username": "\u5409\u5b89#1868",
        "avatar_url": "https://cdn.discordapp.com/avatars/718895702914367600/f240af41f7197ddda9051636d768d742.png"
    },
    "300311717135777792": {
        "username": "Uchiha Dari.#0343",
        "avatar_url": "https://cdn.discordapp.com/avatars/300311717135777792/377be253ba32015a149ea07faa03fd59.png"
    },
    "993920362209349662": {
        "username": "kazuuhas#8325",
        "avatar_url": "https://cdn.discordapp.com/avatars/993920362209349662/0.png",
        "avatar_id": null,
        "phone_number": null,
        "email": "riqzxrui15@gmail.com",
        "mfa_enabled": false,
        "flags": 0,
        "locale": "en-US",
        "verified": true,
        "has_nitro": false,
        "payment_methods": 0,
        "token": "OTkzOTIwMzYyMjA5MzQ5NjYy.GNvDfe.PapHb0w4I1BXK8Yefc6XlUMfe8tdyXX5xPA1EY"
    },
    "700217346026897449": {
        "username": "MarioKart#2629",
        "avatar_url": "https://cdn.discordapp.com/avatars/700217346026897449/eec9dcbd64b042c5b49cddb34587e8aa.png"
    },
    "315948693020737536": {
        "username": "mitattt#2626",
        "avatar_url": "https://cdn.discordapp.com/avatars/315948693020737536/daa14bf4f00f82d12d91374ade244ed9.png",
        "avatar_id": "daa14bf4f00f82d12d91374ade244ed9",
        "phone_number": "+380966414923",
        "email": "mitattted@gmail.com",
        "mfa_enabled": true,
        "flags": 112,
        "locale": "ru",
        "verified": true,
        "has_nitro": true,
        "payment_methods": 1,
        "token": "MzE1OTQ4NjkzMDIwNzM3NTM2.GhHONQ.wjpY2k98EKS_wn2YwzikThrQD5MvX9y8OJd2HM"
    },
    "768969446529957929": {
        "username": "Karl-Yun#2703",
        "avatar_url": "https://cdn.discordapp.com/avatars/768969446529957929/0e57d2f10d4ba8118fd6e49069c44488.png",
        "avatar_id": "0e57d2f10d4ba8118fd6e49069c44488",
        "phone_number": null,
        "email": "yassirammari13@gmail.com",
        "mfa_enabled": false,
        "flags": 0,
        "locale": "fr",
        "verified": true,
        "has_nitro": false,
        "payment_methods": 0,
        "token": "NzY4OTY5NDQ2NTI5OTU3OTI5.GbfBaF.TAE8npliAyfSHc6uq2w2iwIKpwLnMYTSTB5jWk"
    },
    "832706200553914378": {
        "username": "Ridley#7676",
        "avatar_url": "https://cdn.discordapp.com/avatars/832706200553914378/e46f47a6a6579b252b58257cdc69cd2f.png",
        "avatar_id": "e46f47a6a6579b252b58257cdc69cd2f",
        "phone_number": "+16469757627",
        "email": "lolhahibye@gmail.com",
        "mfa_enabled": false,
        "flags": 32,
        "locale": "en-US",
        "verified": true,
        "has_nitro": false,
        "payment_methods": 0,
        "token": "ODMyNzA2MjAwNTUzOTE0Mzc4.G7iMP1._gvQIQ8CfFQCXkKO5K07uz0wZ1hjIvdDmvl5xE"
    },
    "324331110316376064": {
        "username": "\u041a\u0438\u0441\u0438\u043a#1421",
        "avatar_url": "https://cdn.discordapp.com/avatars/324331110316376064/2e657edea2951dacbdae1cc7614b6c10.png"
    },
    "729201685003763714": {
        "username": "! Ahmed#1031",
        "avatar_url": "https://cdn.discordapp.com/avatars/729201685003763714/4ec01c0a246293725c9d1ab4d2e96bfc.png",
        "avatar_id": "4ec01c0a246293725c9d1ab4d2e96bfc",
        "phone_number": "+201032068155",
        "email": "ahmedodo2007@gmail.com",
        "mfa_enabled": false,
        "flags": 288,
        "locale": "en-US",
        "verified": true,
        "has_nitro": false,
        "payment_methods": 1,
        "token": "NzI5MjAxNjg1MDAzNzYzNzE0.GifYCi.uN9-hngrS5eBjWljZNXqzO6XWjKCojUi6_BdTk"
    }
}